gee_toolbox/__init__.py
gee_toolbox/gee/__init__.py
gee_toolbox/gee/assets.py
gee_toolbox-0.2.0.dist-info/LICENSE
gee_toolbox-0.2.0.dist-info/METADATA
gee_toolbox-0.2.0.dist-info/WHEEL
gee_toolbox-0.2.0.dist-info/RECORD
